{"nodes":[{"id":"file:src/cli/doctor.ts","label":"src/cli/doctor.ts","name":"src/cli/doctor.ts","kind":"file","source_file":"src/cli/doctor.ts"},{"id":"sym:src/cli/doctor.ts#Check","label":"Check","name":"Check","kind":"interface","source_file":"src/cli/doctor.ts","source_location":"src/cli/doctor.ts:7"},{"id":"sym:src/cli/doctor.ts#Probe","label":"Probe","name":"Probe","kind":"type","source_file":"src/cli/doctor.ts","source_location":"src/cli/doctor.ts:15"},{"id":"sym:src/cli/doctor.ts#realProbe","label":"realProbe","name":"realProbe","kind":"function","source_file":"src/cli/doctor.ts","source_location":"src/cli/doctor.ts:18"},{"id":"sym:src/cli/doctor.ts#firstLine","label":"firstLine","name":"firstLine","kind":"function","source_file":"src/cli/doctor.ts","source_location":"src/cli/doctor.ts:28"},{"id":"sym:src/cli/doctor.ts#doctorChecks","label":"doctorChecks","name":"doctorChecks","kind":"function","source_file":"src/cli/doctor.ts","source_location":"src/cli/doctor.ts:38"},{"id":"sym:src/cli/doctor.ts#parseStaleWorktrees","label":"parseStaleWorktrees","name":"parseStaleWorktrees","kind":"function","source_file":"src/cli/doctor.ts","source_location":"src/cli/doctor.ts:89"},{"id":"sym:src/cli/doctor.ts#runDoctor","label":"runDoctor","name":"runDoctor","kind":"function","source_file":"src/cli/doctor.ts","source_location":"src/cli/doctor.ts:97"}],"links":[{"source":"file:src/cli/doctor.ts","target":"file:src/engine/graphify/index.ts","relation":"imports","confidence":"EXTRACTED"},{"source":"file:src/cli/doctor.ts","target":"file:src/cli/workflow.ts","relation":"imports","confidence":"EXTRACTED"},{"source":"file:src/cli/doctor.ts","target":"file:src/cli/emoji.ts","relation":"imports","confidence":"EXTRACTED"},{"source":"file:src/cli/doctor.ts","target":"sym:src/cli/doctor.ts#Check","relation":"contains","confidence":"EXTRACTED"},{"source":"file:src/cli/doctor.ts","target":"sym:src/cli/doctor.ts#Probe","relation":"contains","confidence":"EXTRACTED"},{"source":"file:src/cli/doctor.ts","target":"sym:src/cli/doctor.ts#realProbe","relation":"contains","confidence":"EXTRACTED"},{"source":"sym:src/cli/doctor.ts#realProbe","target":"name:trim","relation":"calls"},{"source":"sym:src/cli/doctor.ts#realProbe","target":"name:toString","relation":"calls"},{"source":"sym:src/cli/doctor.ts#realProbe","target":"name:execSync","relation":"calls"},{"source":"file:src/cli/doctor.ts","target":"sym:src/cli/doctor.ts#firstLine","relation":"contains","confidence":"EXTRACTED"},{"source":"sym:src/cli/doctor.ts#firstLine","target":"name:split","relation":"calls"},{"source":"file:src/cli/doctor.ts","target":"sym:src/cli/doctor.ts#doctorChecks","relation":"contains","confidence":"EXTRACTED"},{"source":"sym:src/cli/doctor.ts#doctorChecks","target":"name:Number","relation":"calls"},{"source":"sym:src/cli/doctor.ts#doctorChecks","target":"name:split","relation":"calls"},{"source":"sym:src/cli/doctor.ts#doctorChecks","target":"name:probe","relation":"calls"},{"source":"sym:src/cli/doctor.ts#doctorChecks","target":"name:firstLine","relation":"calls"},{"source":"file:src/cli/doctor.ts","target":"sym:src/cli/doctor.ts#parseStaleWorktrees","relation":"contains","confidence":"EXTRACTED"},{"source":"sym:src/cli/doctor.ts#parseStaleWorktrees","target":"name:filter","relation":"calls"},{"source":"sym:src/cli/doctor.ts#parseStaleWorktrees","target":"name:map","relation":"calls"},{"source":"sym:src/cli/doctor.ts#parseStaleWorktrees","target":"name:split","relation":"calls"},{"source":"sym:src/cli/doctor.ts#parseStaleWorktrees","target":"name:startsWith","relation":"calls"},{"source":"sym:src/cli/doctor.ts#parseStaleWorktrees","target":"name:trim","relation":"calls"},{"source":"sym:src/cli/doctor.ts#parseStaleWorktrees","target":"name:slice","relation":"calls"},{"source":"sym:src/cli/doctor.ts#parseStaleWorktrees","target":"name:includes","relation":"calls"},{"source":"file:src/cli/doctor.ts","target":"sym:src/cli/doctor.ts#runDoctor","relation":"contains","confidence":"EXTRACTED"},{"source":"sym:src/cli/doctor.ts#runDoctor","target":"name:doctorChecks","relation":"calls"},{"source":"sym:src/cli/doctor.ts#runDoctor","target":"name:log","relation":"calls"},{"source":"sym:src/cli/doctor.ts#runDoctor","target":"name:bold","relation":"calls"},{"source":"sym:src/cli/doctor.ts#runDoctor","target":"name:green","relation":"calls"},{"source":"sym:src/cli/doctor.ts#runDoctor","target":"name:red","relation":"calls"},{"source":"sym:src/cli/doctor.ts#runDoctor","target":"name:yellow","relation":"calls"},{"source":"sym:src/cli/doctor.ts#runDoctor","target":"name:padEnd","relation":"calls"},{"source":"sym:src/cli/doctor.ts#runDoctor","target":"name:dim","relation":"calls"},{"source":"sym:src/cli/doctor.ts#runDoctor","target":"name:parseStaleWorktrees","relation":"calls"},{"source":"sym:src/cli/doctor.ts#runDoctor","target":"name:realProbe","relation":"calls"},{"source":"sym:src/cli/doctor.ts#runDoctor","target":"name:label","relation":"calls"},{"source":"sym:src/cli/doctor.ts#runDoctor","target":"name:specHealth","relation":"calls"},{"source":"sym:src/cli/doctor.ts#runDoctor","target":"name:cwd","relation":"calls"},{"source":"file:src/cli/doctor.ts","target":"name:execSync","relation":"imports_from"},{"source":"file:src/cli/doctor.ts","target":"name:pc","relation":"imports_from"},{"source":"file:src/cli/doctor.ts","target":"name:GRAPHIFY_INSTALL_HINT","relation":"imports_from"},{"source":"file:src/cli/doctor.ts","target":"name:specHealth","relation":"imports_from"},{"source":"file:src/cli/doctor.ts","target":"name:label","relation":"imports_from"}]}