{"nodes":[{"id":"file:skills/rivet-spec-author/SKILL.md","label":"skills/rivet-spec-author/SKILL.md","name":"skills/rivet-spec-author/SKILL.md","kind":"file","source_file":"skills/rivet-spec-author/SKILL.md"},{"id":"doc:skills/rivet-spec-author/SKILL.md#Authoring a Rivet spec","label":"Authoring a Rivet spec","name":"Authoring a Rivet spec","kind":"doc","source_file":"skills/rivet-spec-author/SKILL.md","source_location":"skills/rivet-spec-author/SKILL.md:6"},{"id":"doc:skills/rivet-spec-author/SKILL.md#File shape (`.rivet/specs/<feature>.md`) — Gherkin is the default format","label":"File shape (`.rivet/specs/<feature>.md`) — Gherkin is the default format","name":"File shape (`.rivet/specs/<feature>.md`) — Gherkin is the default format","kind":"doc","source_file":"skills/rivet-spec-author/SKILL.md","source_location":"skills/rivet-spec-author/SKILL.md:12"},{"id":"doc:skills/rivet-spec-author/SKILL.md#Generating criteria from a one-line requirement (the scaffold)","label":"Generating criteria from a one-line requirement (the scaffold)","name":"Generating criteria from a one-line requirement (the scaffold)","kind":"doc","source_file":"skills/rivet-spec-author/SKILL.md","source_location":"skills/rivet-spec-author/SKILL.md:47"},{"id":"doc:skills/rivet-spec-author/SKILL.md#Rules (RFC-2119)","label":"Rules (RFC-2119)","name":"Rules (RFC-2119)","kind":"doc","source_file":"skills/rivet-spec-author/SKILL.md","source_location":"skills/rivet-spec-author/SKILL.md:74"},{"id":"doc:skills/rivet-spec-author/SKILL.md#Quality check before handing off","label":"Quality check before handing off","name":"Quality check before handing off","kind":"doc","source_file":"skills/rivet-spec-author/SKILL.md","source_location":"skills/rivet-spec-author/SKILL.md:101"}],"links":[{"source":"file:skills/rivet-spec-author/SKILL.md","target":"doc:skills/rivet-spec-author/SKILL.md#Authoring a Rivet spec","relation":"contains","confidence":"EXTRACTED"},{"source":"file:skills/rivet-spec-author/SKILL.md","target":"doc:skills/rivet-spec-author/SKILL.md#File shape (`.rivet/specs/<feature>.md`) — Gherkin is the default format","relation":"contains","confidence":"EXTRACTED"},{"source":"file:skills/rivet-spec-author/SKILL.md","target":"doc:skills/rivet-spec-author/SKILL.md#Generating criteria from a one-line requirement (the scaffold)","relation":"contains","confidence":"EXTRACTED"},{"source":"file:skills/rivet-spec-author/SKILL.md","target":"doc:skills/rivet-spec-author/SKILL.md#Rules (RFC-2119)","relation":"contains","confidence":"EXTRACTED"},{"source":"file:skills/rivet-spec-author/SKILL.md","target":"doc:skills/rivet-spec-author/SKILL.md#Quality check before handing off","relation":"contains","confidence":"EXTRACTED"}]}