{"nodes":[{"id":"file:src/engine/gatepacks.ts","label":"src/engine/gatepacks.ts","name":"src/engine/gatepacks.ts","kind":"file","source_file":"src/engine/gatepacks.ts"},{"id":"sym:src/engine/gatepacks.ts#PackDef","label":"PackDef","name":"PackDef","kind":"interface","source_file":"src/engine/gatepacks.ts","source_location":"src/engine/gatepacks.ts:12"},{"id":"sym:src/engine/gatepacks.ts#escapeRe","label":"escapeRe","name":"escapeRe","kind":"function","source_file":"src/engine/gatepacks.ts","source_location":"src/engine/gatepacks.ts:18"},{"id":"sym:src/engine/gatepacks.ts#triggered","label":"triggered","name":"triggered","kind":"function","source_file":"src/engine/gatepacks.ts","source_location":"src/engine/gatepacks.ts:22"},{"id":"sym:src/engine/gatepacks.ts#requiredPacks","label":"requiredPacks","name":"requiredPacks","kind":"function","source_file":"src/engine/gatepacks.ts","source_location":"src/engine/gatepacks.ts:31"},{"id":"sym:src/engine/gatepacks.ts#evaluatePack","label":"evaluatePack","name":"evaluatePack","kind":"function","source_file":"src/engine/gatepacks.ts","source_location":"src/engine/gatepacks.ts:36"},{"id":"sym:src/engine/gatepacks.ts#floorViolations","label":"floorViolations","name":"floorViolations","kind":"function","source_file":"src/engine/gatepacks.ts","source_location":"src/engine/gatepacks.ts:61"},{"id":"sym:src/engine/gatepacks.ts#applyGateFloor","label":"applyGateFloor","name":"applyGateFloor","kind":"function","source_file":"src/engine/gatepacks.ts","source_location":"src/engine/gatepacks.ts:73"}],"links":[{"source":"file:src/engine/gatepacks.ts","target":"file:src/engine/spec/ears.ts","relation":"imports","confidence":"EXTRACTED"},{"source":"file:src/engine/gatepacks.ts","target":"file:src/config/schema.ts","relation":"imports","confidence":"EXTRACTED"},{"source":"file:src/engine/gatepacks.ts","target":"file:src/engine/route/classify.ts","relation":"imports","confidence":"EXTRACTED"},{"source":"file:src/engine/gatepacks.ts","target":"sym:src/engine/gatepacks.ts#PackDef","relation":"contains","confidence":"EXTRACTED"},{"source":"file:src/engine/gatepacks.ts","target":"sym:src/engine/gatepacks.ts#escapeRe","relation":"contains","confidence":"EXTRACTED"},{"source":"sym:src/engine/gatepacks.ts#escapeRe","target":"name:replace","relation":"calls"},{"source":"file:src/engine/gatepacks.ts","target":"sym:src/engine/gatepacks.ts#triggered","relation":"contains","confidence":"EXTRACTED"},{"source":"sym:src/engine/gatepacks.ts#triggered","target":"name:entries","relation":"calls"},{"source":"sym:src/engine/gatepacks.ts#triggered","target":"name:some","relation":"calls"},{"source":"sym:src/engine/gatepacks.ts#triggered","target":"name:test","relation":"calls"},{"source":"sym:src/engine/gatepacks.ts#triggered","target":"name:RegExp","relation":"calls"},{"source":"sym:src/engine/gatepacks.ts#triggered","target":"name:escapeRe","relation":"calls"},{"source":"sym:src/engine/gatepacks.ts#triggered","target":"name:push","relation":"calls"},{"source":"sym:src/engine/gatepacks.ts#triggered","target":"name:sort","relation":"calls"},{"source":"file:src/engine/gatepacks.ts","target":"sym:src/engine/gatepacks.ts#requiredPacks","relation":"contains","confidence":"EXTRACTED"},{"source":"sym:src/engine/gatepacks.ts#requiredPacks","target":"name:sort","relation":"calls"},{"source":"sym:src/engine/gatepacks.ts#requiredPacks","target":"name:Set","relation":"calls"},{"source":"sym:src/engine/gatepacks.ts#requiredPacks","target":"name:triggered","relation":"calls"},{"source":"file:src/engine/gatepacks.ts","target":"sym:src/engine/gatepacks.ts#evaluatePack","relation":"contains","confidence":"EXTRACTED"},{"source":"sym:src/engine/gatepacks.ts#evaluatePack","target":"name:RegExp","relation":"calls"},{"source":"sym:src/engine/gatepacks.ts#evaluatePack","target":"name:escapeRe","relation":"calls"},{"source":"sym:src/engine/gatepacks.ts#evaluatePack","target":"name:test","relation":"calls"},{"source":"sym:src/engine/gatepacks.ts#evaluatePack","target":"name:push","relation":"calls"},{"source":"sym:src/engine/gatepacks.ts#evaluatePack","target":"name:Set","relation":"calls"},{"source":"sym:src/engine/gatepacks.ts#evaluatePack","target":"name:flatMap","relation":"calls"},{"source":"sym:src/engine/gatepacks.ts#evaluatePack","target":"name:map","relation":"calls"},{"source":"sym:src/engine/gatepacks.ts#evaluatePack","target":"name:has","relation":"calls"},{"source":"file:src/engine/gatepacks.ts","target":"sym:src/engine/gatepacks.ts#floorViolations","relation":"contains","confidence":"EXTRACTED"},{"source":"sym:src/engine/gatepacks.ts#floorViolations","target":"name:map","relation":"calls"},{"source":"sym:src/engine/gatepacks.ts#floorViolations","target":"name:filter","relation":"calls"},{"source":"sym:src/engine/gatepacks.ts#floorViolations","target":"name:requirementKind","relation":"calls"},{"source":"sym:src/engine/gatepacks.ts#floorViolations","target":"name:some","relation":"calls"},{"source":"file:src/engine/gatepacks.ts","target":"sym:src/engine/gatepacks.ts#applyGateFloor","relation":"contains","confidence":"EXTRACTED"},{"source":"sym:src/engine/gatepacks.ts#applyGateFloor","target":"name:triggered","relation":"calls"},{"source":"sym:src/engine/gatepacks.ts#applyGateFloor","target":"name:join","relation":"calls"},{"source":"file:src/engine/gatepacks.ts","target":"name:isNegativeCriterion","relation":"imports_from"},{"source":"file:src/engine/gatepacks.ts","target":"name:requirementKind","relation":"imports_from"},{"source":"file:src/engine/gatepacks.ts","target":"name:Requirement","relation":"imports_from"},{"source":"file:src/engine/gatepacks.ts","target":"name:RivetConfig","relation":"imports_from"},{"source":"file:src/engine/gatepacks.ts","target":"name:Mode","relation":"imports_from"}]}